proxmark3/__init__.py
proxmark3/proxmark3.py
proxmark3py-0.0.4.dist-info/LICENSE
proxmark3py-0.0.4.dist-info/METADATA
proxmark3py-0.0.4.dist-info/WHEEL
proxmark3py-0.0.4.dist-info/top_level.txt
proxmark3py-0.0.4.dist-info/RECORD
