Metadata-Version: 2.1
Name: proxmark3py
Version: 0.0.4
Summary: A proxmark3 library base on pyserial
Home-page: https://github.com/taichunmin/proxmark3py
Author: Chunmin Tai
Author-email: taichunmin@gmail.com
Project-URL: Bug Tracker, https://github.com/taichunmin/proxmark3py/issues
Keywords: proxmark3,serial,mifare,nfc
Classifier: Programming Language :: Python :: 3
Classifier: License :: OSI Approved :: MIT License
Classifier: Operating System :: OS Independent
Requires-Python: >=3.6
License-File: LICENSE
Requires-Dist: pyserial
